argo_workflows/__init__.py
argo_workflows/api_client.py
argo_workflows/configuration.py
argo_workflows/exceptions.py
argo_workflows/model_utils.py
argo_workflows/rest.py
argo_workflows/api/__init__.py
argo_workflows/api/archived_workflow_service_api.py
argo_workflows/api/artifact_service_api.py
argo_workflows/api/cluster_workflow_template_service_api.py
argo_workflows/api/cron_workflow_service_api.py
argo_workflows/api/event_service_api.py
argo_workflows/api/event_source_service_api.py
argo_workflows/api/info_service_api.py
argo_workflows/api/sensor_service_api.py
argo_workflows/api/workflow_service_api.py
argo_workflows/api/workflow_template_service_api.py
argo_workflows/apis/__init__.py
argo_workflows/model/__init__.py
argo_workflows/model/affinity.py
argo_workflows/model/app_armor_profile.py
argo_workflows/model/aws_elastic_block_store_volume_source.py
argo_workflows/model/azure_disk_volume_source.py
argo_workflows/model/azure_file_volume_source.py
argo_workflows/model/capabilities.py
argo_workflows/model/ceph_fs_volume_source.py
argo_workflows/model/cinder_volume_source.py
argo_workflows/model/cluster_trust_bundle_projection.py
argo_workflows/model/config_map_env_source.py
argo_workflows/model/config_map_key_selector.py
argo_workflows/model/config_map_projection.py
argo_workflows/model/config_map_volume_source.py
argo_workflows/model/container.py
argo_workflows/model/container_port.py
argo_workflows/model/container_resize_policy.py
argo_workflows/model/create_options.py
argo_workflows/model/csi_volume_source.py
argo_workflows/model/downward_api_projection.py
argo_workflows/model/downward_api_volume_file.py
argo_workflows/model/downward_api_volume_source.py
argo_workflows/model/empty_dir_volume_source.py
argo_workflows/model/env_from_source.py
argo_workflows/model/env_var.py
argo_workflows/model/env_var_source.py
argo_workflows/model/ephemeral_volume_source.py
argo_workflows/model/event.py
argo_workflows/model/event_series.py
argo_workflows/model/event_source.py
argo_workflows-6.6.16.dist-info/licenses/LICENSE
argo_workflows-6.6.16.dist-info/METADATA
argo_workflows-6.6.16.dist-info/WHEEL
argo_workflows-6.6.16.dist-info/top_level.txt
argo_workflows-6.6.16.dist-info/RECORD
